tortoise/__init__.py
tortoise/tortoise.py
tortoise-0.1.1.dist-info/LICENSE
tortoise-0.1.1.dist-info/METADATA
tortoise-0.1.1.dist-info/WHEEL
tortoise-0.1.1.dist-info/top_level.txt
tortoise-0.1.1.dist-info/RECORD
