Metadata-Version: 2.1
Name: tortoise
Version: 0.1.1
Summary: Turtle graphics on the web.
Home-page: https://github.com/epeios-q37/tortoise-python
Author: Claude SIMON
License: UNKNOWN
Keywords: turtle,web
Platform: UNKNOWN
Classifier: Environment :: Web Environment
Classifier: Development Status :: 3 - Alpha
Classifier: Intended Audience :: Education
Classifier: Intended Audience :: Other Audience
Classifier: License :: OSI Approved :: MIT License 
Classifier: Operating System :: OS Independent
Classifier: Programming Language :: Python :: 2
Classifier: Programming Language :: Python :: 3
Classifier: Topic :: Education
